.gitignore
CHANGELOG.md
LICENSE.md
MANIFEST.in
README.md
setup.cfg
setup.py
dota2picker/__init__.py
dota2picker/checker.py
dota2picker/csv2pkl.py
dota2picker/database.py
dota2picker/editor.py
dota2picker/model.py
dota2picker/picker.py
dota2picker/pkl2csv.py
dota2picker/version.py
dota2picker/view.py
dota2picker.egg-info/PKG-INFO
dota2picker.egg-info/SOURCES.txt
dota2picker.egg-info/dependency_links.txt
dota2picker.egg-info/entry_points.txt
dota2picker.egg-info/requires.txt
dota2picker.egg-info/top_level.txt
dota2picker/database/Database.csv
dota2picker/database/Database.pkl
dota2picker/images/heroes/Abaddon.png
dota2picker/images/heroes/Alchemist.png
dota2picker/images/heroes/Ancient Apparition.png
dota2picker/images/heroes/Anti-Mage.png
dota2picker/images/heroes/Arc Warden.png
dota2picker/images/heroes/Axe.png
dota2picker/images/heroes/Bane.png
dota2picker/images/heroes/Batrider.png
dota2picker/images/heroes/Beastmaster.png
dota2picker/images/heroes/Bloodseeker.png
dota2picker/images/heroes/Bounty Hunter.png
dota2picker/images/heroes/Brewmaster.png
dota2picker/images/heroes/Bristleback.png
dota2picker/images/heroes/Broodmother.png
dota2picker/images/heroes/Centaur Warrunner.png
dota2picker/images/heroes/Chaos Knight.png
dota2picker/images/heroes/Chen.png
dota2picker/images/heroes/Clinkz.png
dota2picker/images/heroes/Clockwerk.png
dota2picker/images/heroes/Crystal Maiden.png
dota2picker/images/heroes/Dark Seer.png
dota2picker/images/heroes/Dark Willow.png
dota2picker/images/heroes/Dazzle.png
dota2picker/images/heroes/Death Prophet.png
dota2picker/images/heroes/Disruptor.png
dota2picker/images/heroes/Doom.png
dota2picker/images/heroes/Dragon Knight.png
dota2picker/images/heroes/Drow Ranger.png
dota2picker/images/heroes/Earth Spirit.png
dota2picker/images/heroes/Earthshaker.png
dota2picker/images/heroes/Elder Titan.png
dota2picker/images/heroes/Ember Spirit.png
dota2picker/images/heroes/Enchantress.png
dota2picker/images/heroes/Enigma.png
dota2picker/images/heroes/Faceless Void.png
dota2picker/images/heroes/Grimstroke.png
dota2picker/images/heroes/Gyrocopter.png
dota2picker/images/heroes/Huskar.png
dota2picker/images/heroes/Invoker.png
dota2picker/images/heroes/Io.png
